{
  "type": "FeatureCollection",
  "features": [
    {
      "type": "Feature",
      "geometry": {
        "type": "Point",
        "coordinates": [16.3691, 48.203]
      },
      "properties": {
         "id": "pmb15",
         "title": "Oper",
         "lat": "48.203",
         "lon": "16.3691",
         "timestamp": ["1877-06-16", "1877-06-30"],
         "importance": "2"
      }
      }
  ]
}