{
  "type": "FeatureCollection",
  "features": [
    {
      "type": "Feature",
      "geometry": {
        "type": "Point",
        "coordinates": [16.372564182283, 48.201265597319]
      },
      "properties": {
         "id": "pmb516",
         "title": "Musikverein",
         "lat": "48.201265597319",
         "lon": "16.372564182283",
         "timestamp": ["1881-11-27"],
         "importance": "1"
      }
      }, 
    {
      "type": "Feature",
      "geometry": {
        "type": "Point",
        "coordinates": [16.366111, 48.209167]
      },
      "properties": {
         "id": "pmb4",
         "title": "Bösendorfer-Saal",
         "lat": "48.209167",
         "lon": "16.366111",
         "timestamp": ["1881-11-26"],
         "importance": "1"
      }
      }, 
    {
      "type": "Feature",
      "geometry": {
        "type": "Point",
        "coordinates": [16.373056, 48.208333]
      },
      "properties": {
         "id": "pmb50",
         "title": "Wien",
         "lat": "48.208333",
         "lon": "16.373056",
         "timestamp": ["1881-11-01", "1881-11-02", "1881-11-03", "1881-11-04", "1881-11-05", "1881-11-06", "1881-11-07", "1881-11-08", "1881-11-09", "1881-11-10", "1881-11-11", "1881-11-12", "1881-11-13", "1881-11-14", "1881-11-15", "1881-11-16", "1881-11-17", "1881-11-18", "1881-11-19", "1881-11-20", "1881-11-21", "1881-11-22", "1881-11-23", "1881-11-24", "1881-11-25", "1881-11-26", "1881-11-28", "1881-11-29", "1881-11-30"],
         "importance": "29"
      }
      }, 
    {
      "type": "Feature",
      "geometry": {
        "type": "Point",
        "coordinates": [16.35032, 48.19522]
      },
      "properties": {
         "id": "pmb56",
         "title": "VI., Mariahilf",
         "lat": "48.19522",
         "lon": "16.35032",
         "timestamp": ["1881-11-27"],
         "importance": "1"
      }
      }, 
    {
      "type": "Feature",
      "geometry": {
        "type": "Point",
        "coordinates": [16.35, 48.2]
      },
      "properties": {
         "id": "pmb57",
         "title": "VII., Neubau",
         "lat": "48.2",
         "lon": "16.35",
         "timestamp": ["1881-11-27"],
         "importance": "1"
      }
      }
  ]
}