{
  "type": "FeatureCollection",
  "features": [
    {
      "type": "Feature",
      "geometry": {
        "type": "Point",
        "coordinates": [16.373056, 48.208333]
      },
      "properties": {
         "id": "pmb50",
         "title": "Wien",
         "lat": "48.208333",
         "lon": "16.373056",
         "timestamp": ["1882-07-01", "1882-07-02", "1882-07-03", "1882-07-04", "1882-07-05", "1882-07-06", "1882-07-07", "1882-07-08", "1882-07-09", "1882-07-10", "1882-07-11", "1882-07-12", "1882-07-13", "1882-07-14", "1882-07-15", "1882-07-16", "1882-07-17", "1882-07-18", "1882-07-19", "1882-07-20", "1882-07-21", "1882-07-22", "1882-07-23", "1882-07-24", "1882-07-25", "1882-07-26", "1882-07-27", "1882-07-28", "1882-07-29", "1882-07-30"],
         "importance": "30"
      }
      }, 
    {
      "type": "Feature",
      "geometry": {
        "type": "Point",
        "coordinates": [16.363819, 48.20334]
      },
      "properties": {
         "id": "pmb168765",
         "title": "Wohnung und Ordination Johann Schnitzler Burgring 1",
         "lat": "48.20334",
         "lon": "16.363819",
         "timestamp": ["1882-07-01", "1882-07-02", "1882-07-03", "1882-07-04", "1882-07-05", "1882-07-06", "1882-07-07", "1882-07-08", "1882-07-09", "1882-07-10", "1882-07-11", "1882-07-12", "1882-07-13", "1882-07-14", "1882-07-15", "1882-07-16", "1882-07-17", "1882-07-18", "1882-07-19", "1882-07-20", "1882-07-21", "1882-07-22", "1882-07-23", "1882-07-24", "1882-07-25", "1882-07-26", "1882-07-27", "1882-07-28", "1882-07-29", "1882-07-30"],
         "importance": "30"
      }
      }, 
    {
      "type": "Feature",
      "geometry": {
        "type": "Point",
        "coordinates": [9.50266, 47.00601]
      },
      "properties": {
         "id": "pmb7978",
         "title": "Bad Ragaz",
         "lat": "47.00601",
         "lon": "9.50266",
         "timestamp": ["1882-07-31"],
         "importance": "1"
      }
      }
  ]
}