{
  "type": "FeatureCollection",
  "features": [
    {
      "type": "Feature",
      "geometry": {
        "type": "Point",
        "coordinates": [16.373056, 48.208333]
      },
      "properties": {
         "id": "pmb50",
         "title": "Wien",
         "lat": "48.208333",
         "lon": "16.373056",
         "timestamp": ["1884-09-02", "1884-09-03", "1884-09-04", "1884-09-05", "1884-09-06", "1884-09-07", "1884-09-08", "1884-09-09", "1884-09-10", "1884-09-11", "1884-09-12", "1884-09-13", "1884-09-14", "1884-09-15", "1884-09-16", "1884-09-17", "1884-09-18", "1884-09-19", "1884-09-20", "1884-09-21", "1884-09-22", "1884-09-23", "1884-09-24", "1884-09-25", "1884-09-26", "1884-09-27", "1884-09-28", "1884-09-29", "1884-09-30"],
         "importance": "29"
      }
      }, 
    {
      "type": "Feature",
      "geometry": {
        "type": "Point",
        "coordinates": [16.363819, 48.20334]
      },
      "properties": {
         "id": "pmb168765",
         "title": "Wohnung und Ordination Johann Schnitzler Burgring 1",
         "lat": "48.20334",
         "lon": "16.363819",
         "timestamp": ["1884-09-02", "1884-09-03", "1884-09-04", "1884-09-05", "1884-09-06", "1884-09-07", "1884-09-08", "1884-09-09", "1884-09-10", "1884-09-11", "1884-09-12", "1884-09-13", "1884-09-14", "1884-09-15", "1884-09-16", "1884-09-17", "1884-09-18", "1884-09-19", "1884-09-20", "1884-09-21", "1884-09-22", "1884-09-23", "1884-09-24", "1884-09-25", "1884-09-26", "1884-09-27", "1884-09-28", "1884-09-29", "1884-09-30"],
         "importance": "29"
      }
      }, 
    {
      "type": "Feature",
      "geometry": {
        "type": "Point",
        "coordinates": [16.36645, 48.20778]
      },
      "properties": {
         "id": "pmb185621",
         "title": "Burgtheater [Altes Burgtheater]",
         "lat": "48.20778",
         "lon": "16.36645",
         "timestamp": ["1884-09-04", "1884-09-08"],
         "importance": "2"
      }
      }, 
    {
      "type": "Feature",
      "geometry": {
        "type": "Point",
        "coordinates": [13.61893, 47.71109]
      },
      "properties": {
         "id": "pmb213",
         "title": "Bad Ischl",
         "lat": "47.71109",
         "lon": "13.61893",
         "timestamp": ["1884-09-01"],
         "importance": "1"
      }
      }
  ]
}