{
  "type": "FeatureCollection",
  "features": [
    {
      "type": "Feature",
      "geometry": {
        "type": "Point",
        "coordinates": [16.373056, 48.208333]
      },
      "properties": {
         "id": "pmb50",
         "title": "Wien",
         "lat": "48.208333",
         "lon": "16.373056",
         "timestamp": ["1885-04-01", "1885-04-02", "1885-04-03", "1885-04-04", "1885-04-05", "1885-04-06", "1885-04-07", "1885-04-08", "1885-04-09", "1885-04-10", "1885-04-11", "1885-04-12", "1885-04-13", "1885-04-14", "1885-04-15", "1885-04-16", "1885-04-17", "1885-04-18", "1885-04-19", "1885-04-20", "1885-04-21", "1885-04-22", "1885-04-23", "1885-04-24", "1885-04-25", "1885-04-26", "1885-04-27", "1885-04-28", "1885-04-29", "1885-04-30"],
         "importance": "30"
      }
      }, 
    {
      "type": "Feature",
      "geometry": {
        "type": "Point",
        "coordinates": [16.363819, 48.20334]
      },
      "properties": {
         "id": "pmb168765",
         "title": "Wohnung und Ordination Johann Schnitzler Burgring 1",
         "lat": "48.20334",
         "lon": "16.363819",
         "timestamp": ["1885-04-01", "1885-04-02", "1885-04-03", "1885-04-04", "1885-04-05", "1885-04-06", "1885-04-07", "1885-04-08", "1885-04-09", "1885-04-10", "1885-04-11", "1885-04-12", "1885-04-13", "1885-04-14", "1885-04-15", "1885-04-16", "1885-04-17", "1885-04-18", "1885-04-19", "1885-04-20", "1885-04-21", "1885-04-22", "1885-04-23", "1885-04-24", "1885-04-25", "1885-04-26", "1885-04-27", "1885-04-28", "1885-04-29", "1885-04-30"],
         "importance": "30"
      }
      }, 
    {
      "type": "Feature",
      "geometry": {
        "type": "Point",
        "coordinates": [16.384444, 48.215]
      },
      "properties": {
         "id": "pmb118",
         "title": "Carl-Theater",
         "lat": "48.215",
         "lon": "16.384444",
         "timestamp": ["1885-04-07"],
         "importance": "1"
      }
      }, 
    {
      "type": "Feature",
      "geometry": {
        "type": "Point",
        "coordinates": [16.364351, 48.199478]
      },
      "properties": {
         "id": "pmb92603",
         "title": "Wiednertheater",
         "lat": "48.199478",
         "lon": "16.364351",
         "timestamp": ["1885-04-19"],
         "importance": "1"
      }
      }
  ]
}