{
  "type": "FeatureCollection",
  "features": [
    {
      "type": "Feature",
      "geometry": {
        "type": "Point",
        "coordinates": [16.3691, 48.203]
      },
      "properties": {
         "id": "pmb15",
         "title": "Oper",
         "lat": "48.203",
         "lon": "16.3691",
         "timestamp": ["1886-11-19"],
         "importance": "1"
      }
      }, 
    {
      "type": "Feature",
      "geometry": {
        "type": "Point",
        "coordinates": [16.373056, 48.208333]
      },
      "properties": {
         "id": "pmb50",
         "title": "Wien",
         "lat": "48.208333",
         "lon": "16.373056",
         "timestamp": ["1886-11-01", "1886-11-02", "1886-11-03", "1886-11-04", "1886-11-05", "1886-11-06", "1886-11-07", "1886-11-08", "1886-11-09", "1886-11-10", "1886-11-11", "1886-11-12", "1886-11-13", "1886-11-14", "1886-11-15", "1886-11-16", "1886-11-17", "1886-11-18", "1886-11-19", "1886-11-20", "1886-11-21", "1886-11-22", "1886-11-23", "1886-11-24", "1886-11-25", "1886-11-26", "1886-11-27", "1886-11-28", "1886-11-29", "1886-11-30"],
         "importance": "30"
      }
      }, 
    {
      "type": "Feature",
      "geometry": {
        "type": "Point",
        "coordinates": [16.3589845, 48.2195962]
      },
      "properties": {
         "id": "pmb182762",
         "title": "Danzer’s Orpheum",
         "lat": "48.2195962",
         "lon": "16.3589845",
         "timestamp": ["1886-11-20"],
         "importance": "1"
      }
      }, 
    {
      "type": "Feature",
      "geometry": {
        "type": "Point",
        "coordinates": [16.2353, 48.0096]
      },
      "properties": {
         "id": "pmb190818",
         "title": "Stadttheater Baden",
         "lat": "48.0096",
         "lon": "16.2353",
         "timestamp": ["1886-11-14"],
         "importance": "1"
      }
      }
  ]
}