{
  "type": "FeatureCollection",
  "features": [
    {
      "type": "Feature",
      "geometry": {
        "type": "Point",
        "coordinates": [16.373056, 48.208333]
      },
      "properties": {
         "id": "pmb50",
         "title": "Wien",
         "lat": "48.208333",
         "lon": "16.373056",
         "timestamp": ["1887-06-01", "1887-06-02", "1887-06-03", "1887-06-04", "1887-06-05", "1887-06-06", "1887-06-07", "1887-06-08", "1887-06-09", "1887-06-10", "1887-06-11", "1887-06-12", "1887-06-13", "1887-06-14", "1887-06-15", "1887-06-16", "1887-06-17", "1887-06-18", "1887-06-19", "1887-06-20", "1887-06-21", "1887-06-22", "1887-06-23", "1887-06-24", "1887-06-25", "1887-06-26", "1887-06-27", "1887-06-28", "1887-06-29", "1887-06-30"],
         "importance": "30"
      }
      }, 
    {
      "type": "Feature",
      "geometry": {
        "type": "Point",
        "coordinates": [16.363819, 48.20334]
      },
      "properties": {
         "id": "pmb168765",
         "title": "Wohnung und Ordination Johann Schnitzler Burgring 1",
         "lat": "48.20334",
         "lon": "16.363819",
         "timestamp": ["1887-06-01", "1887-06-02", "1887-06-03", "1887-06-04", "1887-06-05", "1887-06-06", "1887-06-07", "1887-06-08", "1887-06-09", "1887-06-10", "1887-06-11", "1887-06-12", "1887-06-13", "1887-06-14", "1887-06-15", "1887-06-16", "1887-06-17", "1887-06-18", "1887-06-19", "1887-06-20", "1887-06-21", "1887-06-22", "1887-06-23", "1887-06-24", "1887-06-25", "1887-06-26", "1887-06-27", "1887-06-28", "1887-06-29", "1887-06-30"],
         "importance": "30"
      }
      }, 
    {
      "type": "Feature",
      "geometry": {
        "type": "Point",
        "coordinates": [16.36645, 48.20778]
      },
      "properties": {
         "id": "pmb185621",
         "title": "Burgtheater [Altes Burgtheater]",
         "lat": "48.20778",
         "lon": "16.36645",
         "timestamp": ["1887-06-08", "1887-06-12", "1887-06-16", "1887-06-20", "1887-06-24", "1887-06-28"],
         "importance": "6"
      }
      }
  ]
}